mtoml/__init__.py
mtoml/mtoml.py
mtoml-1.2.0.dist-info/LICENSE
mtoml-1.2.0.dist-info/METADATA
mtoml-1.2.0.dist-info/WHEEL
mtoml-1.2.0.dist-info/top_level.txt
mtoml-1.2.0.dist-info/RECORD
