Metadata-Version: 2.1
Name: mtoml
Version: 1.2.0
Summary: Manage multiple TOML configurations from a single module.
Home-page: https://github.com/wuotes/mtoml
Author: Jordan Schaffrin
Author-email: mailbox@xrtuen.com
License: Mozilla Public License 2.0
Download-URL: https://pypi.org/project/mtoml/
Platform: UNKNOWN
Classifier: License :: OSI Approved :: Mozilla Public License 2.0 (MPL 2.0)
Classifier: Programming Language :: Python :: 3.9
Classifier: Programming Language :: Python :: 3.10
Classifier: Programming Language :: Python :: 3.11
Classifier: Programming Language :: Python :: 3.12
Classifier: Operating System :: Microsoft :: Windows
Classifier: Operating System :: POSIX :: Linux
Classifier: Operating System :: MacOS
Requires-Python: >=3.9
License-File: LICENSE
Requires-Dist: tomli (>=2.0.1)
Requires-Dist: tomli-w (>=1.0.0)
